lowdown/__init__.py
lowdown/_version.py
lowdown/lowdown.css
Lowdown-0.2.1.dist-info/LICENSE.txt
Lowdown-0.2.1.dist-info/METADATA
Lowdown-0.2.1.dist-info/WHEEL
Lowdown-0.2.1.dist-info/top_level.txt
Lowdown-0.2.1.dist-info/RECORD
