Metadata-Version: 2.1
Name: Lowdown
Version: 0.2.1
Summary: Sphinx extension for release notes / changelogs.
Home-page: https://bitbucket.org/ftrack/lowdown
Author: ftrack
Author-email: support@ftrack.com
License: Apache License (2.0)
Keywords: python,sphinx,changelog,release notes
Platform: UNKNOWN
Classifier: License :: OSI Approved :: Apache Software License
Classifier: Intended Audience :: Developers
Classifier: Programming Language :: Python :: 2
Classifier: Programming Language :: Python :: 3
Requires-Python: >=2.7, <4.0
Requires-Dist: docutils (<0.17,>=0.11)
Requires-Dist: arrow (<1,>=0.4.4)
